cornflake/__init__.py
cornflake/exceptions.py
cornflake/fields.py
cornflake/serializers.py
cornflake/sqlalchemy_orm.py
cornflake/utils.py
cornflake/validators.py
cornflake-0.2.4.dist-info/LICENSE.txt
cornflake-0.2.4.dist-info/METADATA
cornflake-0.2.4.dist-info/WHEEL
cornflake-0.2.4.dist-info/top_level.txt
cornflake-0.2.4.dist-info/RECORD
